ml/__init__.py
ml/simple.py
the1owl-0.0.8.dist-info/LICENSE
the1owl-0.0.8.dist-info/METADATA
the1owl-0.0.8.dist-info/WHEEL
the1owl-0.0.8.dist-info/top_level.txt
the1owl-0.0.8.dist-info/RECORD
