Metadata-Version: 2.1
Name: the1owl
Version: 0.0.8
Summary: the1owl Python module
Home-page: http://the1owl.com
Author: the1owl
Author-email: the1owlML@hotmail.com
License: MIT
Platform: UNKNOWN
Classifier: Programming Language :: Python :: 3
Classifier: License :: OSI Approved :: MIT License
Classifier: Operating System :: OS Independent
Requires-Dist: scipy
Requires-Dist: numpy
Requires-Dist: pandas
Requires-Dist: matplotlib
Requires-Dist: sklearn
